timeview/__init__.py
timeview/__main__.py
timeview/__version__.py
timeview/api.py
timeview/dsp/__init__.py
timeview/dsp/dsp.py
timeview/dsp/processing.py
timeview/dsp/tracking.py
timeview/dsp/viterbi.py
timeview/gui/TimeView.icns
timeview/gui/TimeView.qch
timeview/gui/TimeView.qhc
timeview/gui/__init__.py
timeview/gui/dialogs.py
timeview/gui/display_panel.py
timeview/gui/extra.py
timeview/gui/model.py
timeview/gui/plot_area.py
timeview/gui/plot_objects.py
timeview/gui/rendering.py
timeview/gui/view_table.py
timeview/gui/viewer.py
timeview/manager/__init__.py
timeview/manager/dataset_manager.py
timeview/manager/dataset_manager_model.py
timeview/manager/main.ui
timeview-0.1.2.dist-info/METADATA
timeview-0.1.2.dist-info/RECORD
timeview-0.1.2.dist-info/WHEEL
timeview-0.1.2.dist-info/entry_points.txt
timeview-0.1.2.dist-info/top_level.txt
