Metadata-Version: 2.1
Name: timeview
Version: 0.1.2
Summary: A GUI application to view and analyze time series signal data
Home-page: https://github.com/j9ac9k/timeview
Author: Ognyan Moore
Author-email: ognyan.moore@gmail.com
License: MIT
Keywords: timeview gui pyqt signal spectrogram
Platform: UNKNOWN
Classifier: Development Status :: 3 - Alpha
Classifier: Programming Language :: Python :: 3.6
Classifier: Programming Language :: Python :: 3.7
Classifier: Topic :: Scientific/Engineering
Classifier: Topic :: Multimedia :: Sound/Audio :: Analysis
Classifier: Topic :: Utilities
Classifier: Intended Audience :: Science/Research
Classifier: License :: OSI Approved :: MIT License
Requires-Python: >=3.6.0
Provides-Extra: dev
Provides-Extra: test
Requires-Dist: numpy
Requires-Dist: scipy
Requires-Dist: sqlalchemy
Requires-Dist: numba
Requires-Dist: pyqt5
Requires-Dist: qtpy
Requires-Dist: pyqtgraph
Requires-Dist: qtawesome
Requires-Dist: pyedflib
Requires-Dist: cython
Provides-Extra: dev
Requires-Dist: black; extra == 'dev'
Requires-Dist: pre-config; extra == 'dev'
Requires-Dist: flake8-mypy; extra == 'dev'
Requires-Dist: flake8-bugbear; extra == 'dev'
Provides-Extra: test
Requires-Dist: pytest; extra == 'test'
Requires-Dist: pytest-qt; extra == 'test'
Requires-Dist: pytest-runner; extra == 'test'
